enstools/compression/__init__.py
enstools/compression/api.py
enstools/compression/cli.py
enstools/compression/compressor.py
enstools/compression/emulation.py
enstools/compression/errors.py
enstools/compression/evaluator.py
enstools/compression/h5netcdf_compressor.py
enstools/compression/metrics.py
enstools/compression/plugins.py
enstools/compression/pruner.py
enstools/compression/significant_bits.py
enstools/compression/size_metrics.py
enstools/compression/slicing.py
enstools/compression/xr_accessor.py
enstools/compression/analyzer/__init__.py
enstools/compression/analyzer/analysis_options.py
enstools/compression/analyzer/analyze_data_array.py
enstools/compression/analyzer/analyzer.py
enstools/compression/analyzer/analyzer_utils.py
enstools/compression/emulators/__init__.py
enstools/compression/emulators/emulator_class.py
enstools/compression/emulators/filters_emulator.py
enstools/compression/emulators/libpressio_emulator.py
enstools/compression/emulators/zfp_emulator.py
enstools_compression-2023.11.1.dist-info/LICENSE
enstools_compression-2023.11.1.dist-info/METADATA
enstools_compression-2023.11.1.dist-info/WHEEL
enstools_compression-2023.11.1.dist-info/entry_points.txt
enstools_compression-2023.11.1.dist-info/top_level.txt
enstools_compression-2023.11.1.dist-info/RECORD
