Metadata-Version: 2.1
Name: enstools-compression
Version: 2023.11.1
Home-page: https://github.com/wavestoweather/enstools-compression
Author: Oriol Tintó
Author-email: oriol.tinto@lmu.de
License-File: LICENSE
Requires-Dist: enstools >=2023.1
Requires-Dist: enstools-encoding >=2023.6
Requires-Dist: zfpy
Requires-Dist: hdf5plugin >=4.1.3
Requires-Dist: netCDF4
Provides-Extra: examples
Requires-Dist: pooch ; extra == 'examples'
Provides-Extra: test
Requires-Dist: pytest ; extra == 'test'
Requires-Dist: pytest-mock ; extra == 'test'
Requires-Dist: pooch ; extra == 'test'
